[
  {
    "_id": {
      "$oid": "6a4352a2128caa7df65141df"
    },
    "productCode": "MC",
    "productName": "mái cột",
    "logType": "Sửa sản phẩm",
    "logAction": "Không có dữ liệu",
    "createdBy": "LÊ SỸ BÁCH",
    "createdAt": {
      "$date": "2026-06-17T07:16:53Z"
    },
    "updatedAt": {
      "$date": "2026-06-17T07:16:53Z"
    },
    "__v": 0
  },
  {
    "_id": {
      "$oid": "6a4352a2128caa7df65141e0"
    },
    "productCode": "BT",
    "productName": "Búi tròn nhỏ",
    "logType": "Sửa sản phẩm",
    "logAction": "Không có dữ liệu",
    "createdBy": "LÊ SỸ BÁCH",
    "createdAt": {
      "$date": "2026-06-17T07:15:08Z"
    },
    "updatedAt": {
      "$date": "2026-06-17T07:15:08Z"
    },
    "__v": 0
  },
  {
    "_id": {
      "$oid": "6a4352a2128caa7df65141e1"
    },
    "productCode": "LC",
    "productName": "Lưới chùm tóc 2508",
    "logType": "Sửa sản phẩm",
    "logAction": "Không có dữ liệu",
    "createdBy": "LÊ SỸ BÁCH",
    "createdAt": {
      "$date": "2026-06-17T06:51:50Z"
    },
    "updatedAt": {
      "$date": "2026-06-17T06:51:50Z"
    },
    "__v": 0
  },
  {
    "_id": {
      "$oid": "6a4352a2128caa7df65141e2"
    },
    "productCode": "KU",
    "productName": "kem ủ tóc LADYSTARS",
    "logType": "Sửa sản phẩm",
    "logAction": "Không có dữ liệu",
    "createdBy": "LÊ SỸ BÁCH",
    "createdAt": {
      "$date": "2026-06-17T05:33:35Z"
    },
    "updatedAt": {
      "$date": "2026-06-17T05:33:35Z"
    },
    "__v": 0
  },
  {
    "_id": {
      "$oid": "6a4352a2128caa7df65141e3"
    },
    "productCode": "MINH-080425",
    "productName": "Đầu đội siêu da silk base DDVc",
    "logType": "Sửa sản phẩm",
    "logAction": "Sửa giá bán",
    "createdBy": "LÊ SỸ BÁCH",
    "createdAt": {
      "$date": "2026-06-03T03:28:35Z"
    },
    "updatedAt": {
      "$date": "2026-06-03T03:28:35Z"
    },
    "__v": 0
  },
  {
    "_id": {
      "$oid": "6a4352a2128caa7df65141e4"
    },
    "productCode": "N502102",
    "productName": "NGOẠM XOĂN N502102",
    "logType": "Sửa sản phẩm",
    "logAction": "Sửa giá bán",
    "createdBy": "LÊ SỸ BÁCH",
    "createdAt": {
      "$date": "2026-05-05T03:51:29Z"
    },
    "updatedAt": {
      "$date": "2026-05-05T03:51:29Z"
    },
    "__v": 0
  },
  {
    "_id": {
      "$oid": "6a4352a2128caa7df65141e5"
    },
    "productCode": "DDN150126",
    "productName": "Đầu đội xoăn trung niên DDN150126",
    "logType": "Sửa sản phẩm",
    "logAction": "Sửa giá bán",
    "createdBy": "LÊ SỸ BÁCH",
    "createdAt": {
      "$date": "2026-04-29T08:43:42Z"
    },
    "updatedAt": {
      "$date": "2026-04-29T08:43:42Z"
    },
    "__v": 0
  },
  {
    "_id": {
      "$oid": "6a4352a2128caa7df65141e6"
    },
    "productCode": "DDN100124",
    "productName": "Đầu đội machine weft DDN100124",
    "logType": "Sửa sản phẩm",
    "logAction": "Sửa giá bán",
    "createdBy": "LÊ SỸ BÁCH",
    "createdAt": {
      "$date": "2026-04-11T02:54:04Z"
    },
    "updatedAt": {
      "$date": "2026-04-11T02:54:04Z"
    },
    "__v": 0
  },
  {
    "_id": {
      "$oid": "6a4352a2128caa7df65141e7"
    },
    "productCode": "UNKNOWN.9",
    "productName": "UNKNOWN",
    "logType": "Xóa sản phẩm",
    "logAction": "Không có dữ liệu",
    "createdBy": "LÊ SỸ BÁCH",
    "createdAt": {
      "$date": "2026-04-02T07:52:30Z"
    },
    "updatedAt": {
      "$date": "2026-04-02T07:52:30Z"
    },
    "__v": 0
  },
  {
    "_id": {
      "$oid": "6a4352a2128caa7df65141e8"
    },
    "productCode": "MHNU030226",
    "productName": "Mái phủ hói siêu da silk base MHNU030226",
    "logType": "Sửa sản phẩm",
    "logAction": "Sửa giá bán",
    "createdBy": "LÊ SỸ BÁCH",
    "createdAt": {
      "$date": "2026-02-03T04:41:51Z"
    },
    "updatedAt": {
      "$date": "2026-02-03T04:41:51Z"
    },
    "__v": 0
  },
  {
    "_id": {
      "$oid": "6a4352a2128caa7df65141e9"
    },
    "productCode": "MHNU0302266",
    "productName": "Mái phủ hói siêu da silk base MHNU0302266",
    "logType": "Sửa sản phẩm",
    "logAction": "Sửa giá bán",
    "createdBy": "LÊ SỸ BÁCH",
    "createdAt": {
      "$date": "2026-02-03T04:23:47Z"
    },
    "updatedAt": {
      "$date": "2026-02-03T04:23:47Z"
    },
    "__v": 0
  },
  {
    "_id": {
      "$oid": "6a4352a2128caa7df65141ea"
    },
    "productCode": "TNU030226",
    "productName": "TÉM XOĂN TNU030226",
    "logType": "Sửa sản phẩm",
    "logAction": "Không có dữ liệu",
    "createdBy": "LÊ SỸ BÁCH",
    "createdAt": {
      "$date": "2026-02-03T03:44:00Z"
    },
    "updatedAt": {
      "$date": "2026-02-03T03:44:00Z"
    },
    "__v": 0
  },
  {
    "_id": {
      "$oid": "6a4352a2128caa7df65141eb"
    },
    "productCode": "MHNU0302264",
    "productName": "Mái phủ hói siêu da silk base MHNU0302264",
    "logType": "Sửa sản phẩm",
    "logAction": "Sửa giá bán",
    "createdBy": "LÊ SỸ BÁCH",
    "createdAt": {
      "$date": "2026-02-03T03:41:10Z"
    },
    "updatedAt": {
      "$date": "2026-02-03T03:41:10Z"
    },
    "__v": 0
  },
  {
    "_id": {
      "$oid": "6a4352a2128caa7df65141ec"
    },
    "productCode": "MHNA2901261",
    "productName": "Mái phủ hói nam MHNA2901261",
    "logType": "Sửa sản phẩm",
    "logAction": "Không có dữ liệu",
    "createdBy": "LÊ SỸ BÁCH",
    "createdAt": {
      "$date": "2026-01-29T04:10:20Z"
    },
    "updatedAt": {
      "$date": "2026-01-29T04:10:20Z"
    },
    "__v": 0
  },
  {
    "_id": {
      "$oid": "6a4352a2128caa7df65141ed"
    },
    "productCode": "DDN230126",
    "productName": "Nguyên đầu xoăn trung niên DDN230126",
    "logType": "Sửa sản phẩm",
    "logAction": "Sửa giá bán",
    "createdBy": "LÊ SỸ BÁCH",
    "createdAt": {
      "$date": "2026-01-23T07:09:01Z"
    },
    "updatedAt": {
      "$date": "2026-01-23T07:09:01Z"
    },
    "__v": 0
  },
  {
    "_id": {
      "$oid": "6a4352a2128caa7df65141ee"
    },
    "productCode": "TNU230126",
    "productName": "Tóc tém TNU230126",
    "logType": "Sửa sản phẩm",
    "logAction": "Không có dữ liệu",
    "createdBy": "LÊ SỸ BÁCH",
    "createdAt": {
      "$date": "2026-01-23T05:35:48Z"
    },
    "updatedAt": {
      "$date": "2026-01-23T05:35:48Z"
    },
    "__v": 0
  },
  {
    "_id": {
      "$oid": "6a4352a2128caa7df65141ef"
    },
    "productCode": "TLV451601234",
    "productName": "TÓC LÔNG VŨ 451601234 ĐEN",
    "logType": "Sửa sản phẩm",
    "logAction": "Sửa giá nhập",
    "createdBy": "LÊ SỸ BÁCH",
    "createdAt": {
      "$date": "2026-01-17T08:33:06Z"
    },
    "updatedAt": {
      "$date": "2026-01-17T08:33:06Z"
    },
    "__v": 0
  },
  {
    "_id": {
      "$oid": "6a4352a2128caa7df65141f0"
    },
    "productCode": "TLV451601234",
    "productName": "TÓC LÔNG VŨ 451601234 ĐEN",
    "logType": "Sửa sản phẩm",
    "logAction": "Sửa giá nhập",
    "createdBy": "LÊ SỸ BÁCH",
    "createdAt": {
      "$date": "2026-01-17T08:24:04Z"
    },
    "updatedAt": {
      "$date": "2026-01-17T08:24:04Z"
    },
    "__v": 0
  },
  {
    "_id": {
      "$oid": "6a4352a2128caa7df65141f1"
    },
    "productCode": "DDN271225",
    "productName": "Đầu đội ngôi 271225",
    "logType": "Sửa sản phẩm",
    "logAction": "Sửa giá bán",
    "createdBy": "LÊ SỸ BÁCH",
    "createdAt": {
      "$date": "2026-01-16T11:20:51Z"
    },
    "updatedAt": {
      "$date": "2026-01-16T11:20:51Z"
    },
    "__v": 0
  },
  {
    "_id": {
      "$oid": "6a4352a2128caa7df65141f2"
    },
    "productCode": "N150126",
    "productName": "NGOẠM NÂU HẠT DẺ",
    "logType": "Sửa sản phẩm",
    "logAction": "Không có dữ liệu",
    "createdBy": "LÊ SỸ BÁCH",
    "createdAt": {
      "$date": "2026-01-15T08:58:19Z"
    },
    "updatedAt": {
      "$date": "2026-01-15T08:58:19Z"
    },
    "__v": 0
  },
  {
    "_id": {
      "$oid": "6a4352a2128caa7df65141f3"
    },
    "productCode": "DDN150126",
    "productName": "Đầu đội xoăn trung niên DDN150126",
    "logType": "Sửa sản phẩm",
    "logAction": "Không có dữ liệu",
    "createdBy": "LÊ SỸ BÁCH",
    "createdAt": {
      "$date": "2026-01-15T08:27:21Z"
    },
    "updatedAt": {
      "$date": "2026-01-15T08:27:21Z"
    },
    "__v": 0
  },
  {
    "_id": {
      "$oid": "6a4352a2128caa7df65141f4"
    },
    "productCode": "MHNU 2710",
    "productName": "Mái hói nữ 2710",
    "logType": "Sửa sản phẩm",
    "logAction": "Không có dữ liệu",
    "createdBy": "LÊ SỸ BÁCH",
    "createdAt": {
      "$date": "2026-01-14T09:36:45Z"
    },
    "updatedAt": {
      "$date": "2026-01-14T09:36:45Z"
    },
    "__v": 0
  },
  {
    "_id": {
      "$oid": "6a4352a2128caa7df65141f5"
    },
    "productCode": "MHNU2010",
    "productName": "MÁI HÓI NỮ MHNU2010",
    "logType": "Sửa sản phẩm",
    "logAction": "Sửa giá bán",
    "createdBy": "LÊ SỸ BÁCH",
    "createdAt": {
      "$date": "2026-01-14T09:33:34Z"
    },
    "updatedAt": {
      "$date": "2026-01-14T09:33:34Z"
    },
    "__v": 0
  },
  {
    "_id": {
      "$oid": "6a4352a2128caa7df65141f6"
    },
    "productCode": "HÀ-250825",
    "productName": "Đầu đội siêu da silk base DDV250825",
    "logType": "Sửa sản phẩm",
    "logAction": "Sửa giá bán",
    "createdBy": "LÊ SỸ BÁCH",
    "createdAt": {
      "$date": "2026-01-13T10:46:37Z"
    },
    "updatedAt": {
      "$date": "2026-01-13T10:46:37Z"
    },
    "__v": 0
  },
  {
    "_id": {
      "$oid": "6a4352a2128caa7df65141f7"
    },
    "productCode": "MHNU1301266",
    "productName": "Mái phủ hói siêu da silk base MHNU1301266",
    "logType": "Sửa sản phẩm",
    "logAction": "Không có dữ liệu",
    "createdBy": "LÊ SỸ BÁCH",
    "createdAt": {
      "$date": "2026-01-13T10:19:42Z"
    },
    "updatedAt": {
      "$date": "2026-01-13T10:19:42Z"
    },
    "__v": 0
  },
  {
    "_id": {
      "$oid": "6a4352a2128caa7df65141f8"
    },
    "productCode": "MHNU130126",
    "productName": "Mái phủ hói siêu da silk base MHNU130126",
    "logType": "Sửa sản phẩm",
    "logAction": "Sửa giá nhập",
    "createdBy": "LÊ SỸ BÁCH",
    "createdAt": {
      "$date": "2026-01-13T09:54:35Z"
    },
    "updatedAt": {
      "$date": "2026-01-13T09:54:35Z"
    },
    "__v": 0
  },
  {
    "_id": {
      "$oid": "6a4352a2128caa7df65141f9"
    },
    "productCode": "MHNU1301261",
    "productName": "Mái phủ hói siêu da silk base MHNU1301261",
    "logType": "Sửa sản phẩm",
    "logAction": "Sửa giá nhập",
    "createdBy": "LÊ SỸ BÁCH",
    "createdAt": {
      "$date": "2026-01-13T09:54:13Z"
    },
    "updatedAt": {
      "$date": "2026-01-13T09:54:13Z"
    },
    "__v": 0
  },
  {
    "_id": {
      "$oid": "6a4352a2128caa7df65141fa"
    },
    "productCode": "minh-090126",
    "productName": "Đầu đội siêu da silk base DDV090126",
    "logType": "Sửa sản phẩm",
    "logAction": "Không có dữ liệu",
    "createdBy": "LÊ SỸ BÁCH",
    "createdAt": {
      "$date": "2026-01-09T03:23:23Z"
    },
    "updatedAt": {
      "$date": "2026-01-09T03:23:23Z"
    },
    "__v": 0
  },
  {
    "_id": {
      "$oid": "6a4352a2128caa7df65141fb"
    },
    "productCode": "DDX1806-24",
    "productName": "Đầu đội xoáy machine weft DDX1806-24",
    "logType": "Sửa sản phẩm",
    "logAction": "Không có dữ liệu",
    "createdBy": "LÊ SỸ BÁCH",
    "createdAt": {
      "$date": "2025-12-23T08:05:10Z"
    },
    "updatedAt": {
      "$date": "2025-12-23T08:05:10Z"
    },
    "__v": 0
  },
  {
    "_id": {
      "$oid": "6a4352a2128caa7df65141fc"
    },
    "productCode": "hân-2107251",
    "productName": "Mái phủ hói siêu da silk base MHNU2107251",
    "logType": "Sửa sản phẩm",
    "logAction": "Sửa giá nhập",
    "createdBy": "LÊ SỸ BÁCH",
    "createdAt": {
      "$date": "2025-12-21T08:23:20Z"
    },
    "updatedAt": {
      "$date": "2025-12-21T08:23:20Z"
    },
    "__v": 0
  },
  {
    "_id": {
      "$oid": "6a4352a2128caa7df65141fd"
    },
    "productCode": "MHNU0812255",
    "productName": "Mái hói siêu da silk base MHNU0812255",
    "logType": "Sửa sản phẩm",
    "logAction": "Không có dữ liệu",
    "createdBy": "LÊ SỸ BÁCH",
    "createdAt": {
      "$date": "2025-12-08T09:54:52Z"
    },
    "updatedAt": {
      "$date": "2025-12-08T09:54:52Z"
    },
    "__v": 0
  },
  {
    "_id": {
      "$oid": "6a4352a2128caa7df65141fe"
    },
    "productCode": "DDN2811251",
    "productName": "Đầu đội machine weft DDN2811251",
    "logType": "Sửa sản phẩm",
    "logAction": "Sửa giá bán",
    "createdBy": "LÊ SỸ BÁCH",
    "createdAt": {
      "$date": "2025-11-28T03:40:32Z"
    },
    "updatedAt": {
      "$date": "2025-11-28T03:40:32Z"
    },
    "__v": 0
  },
  {
    "_id": {
      "$oid": "6a4352a2128caa7df65141ff"
    },
    "productCode": "MHNU0108241",
    "productName": "MÁI PHỦ HÓI SIÊU DA MHNU0108241",
    "logType": "Sửa sản phẩm",
    "logAction": "Sửa giá bán",
    "createdBy": "LÊ SỸ BÁCH",
    "createdAt": {
      "$date": "2025-11-28T02:35:31Z"
    },
    "updatedAt": {
      "$date": "2025-11-28T02:35:31Z"
    },
    "__v": 0
  },
  {
    "_id": {
      "$oid": "6a4352a2128caa7df6514200"
    },
    "productCode": "MHNU0108241",
    "productName": "MÁI PHỦ HÓI SIÊU DA MHNU0108241",
    "logType": "Sửa sản phẩm",
    "logAction": "Sửa giá bán",
    "createdBy": "LÊ SỸ BÁCH",
    "createdAt": {
      "$date": "2025-11-28T02:34:56Z"
    },
    "updatedAt": {
      "$date": "2025-11-28T02:34:56Z"
    },
    "__v": 0
  },
  {
    "_id": {
      "$oid": "6a4352a2128caa7df6514201"
    },
    "productCode": "MHNU010824",
    "productName": "MÁI PHỦ HÓI SIÊU DA MHNU010824",
    "logType": "Sửa sản phẩm",
    "logAction": "Sửa giá bán",
    "createdBy": "LÊ SỸ BÁCH",
    "createdAt": {
      "$date": "2025-11-28T02:34:10Z"
    },
    "updatedAt": {
      "$date": "2025-11-28T02:34:10Z"
    },
    "__v": 0
  },
  {
    "_id": {
      "$oid": "6a4352a2128caa7df6514202"
    },
    "productCode": "hân-191125",
    "productName": "Mái phủ hói siêu da silk base MHNU191125",
    "logType": "Sửa sản phẩm",
    "logAction": "Sửa giá bán",
    "createdBy": "LÊ SỸ BÁCH",
    "createdAt": {
      "$date": "2025-11-28T02:33:26Z"
    },
    "updatedAt": {
      "$date": "2025-11-28T02:33:26Z"
    },
    "__v": 0
  },
  {
    "_id": {
      "$oid": "6a4352a2128caa7df6514203"
    },
    "productCode": "UNKNOWN.37",
    "productName": "sửa tóc cô liên",
    "logType": "Sửa sản phẩm",
    "logAction": "Sửa giá nhập",
    "createdBy": "LÊ SỸ BÁCH",
    "createdAt": {
      "$date": "2025-11-22T05:13:48Z"
    },
    "updatedAt": {
      "$date": "2025-11-22T05:13:48Z"
    },
    "__v": 0
  },
  {
    "_id": {
      "$oid": "6a4352a2128caa7df6514204"
    },
    "productCode": "UNKNOWN.38",
    "productName": "sửa tóc cô liên",
    "logType": "Sửa sản phẩm",
    "logAction": "Sửa giá nhập",
    "createdBy": "LÊ SỸ BÁCH",
    "createdAt": {
      "$date": "2025-11-22T05:12:54Z"
    },
    "updatedAt": {
      "$date": "2025-11-22T05:12:54Z"
    },
    "__v": 0
  },
  {
    "_id": {
      "$oid": "6a4352a2128caa7df6514205"
    },
    "productCode": "HÂN-1911251",
    "productName": "Đầu đội siêu da silk base DDV1911251",
    "logType": "Sửa sản phẩm",
    "logAction": "Sửa giá nhập",
    "createdBy": "LÊ SỸ BÁCH",
    "createdAt": {
      "$date": "2025-11-19T04:26:50Z"
    },
    "updatedAt": {
      "$date": "2025-11-19T04:26:50Z"
    },
    "__v": 0
  },
  {
    "_id": {
      "$oid": "6a4352a2128caa7df6514206"
    },
    "productCode": "hà-191125",
    "productName": "Đầu đội siêu da silk base DDV191125",
    "logType": "Sửa sản phẩm",
    "logAction": "Không có dữ liệu",
    "createdBy": "LÊ SỸ BÁCH",
    "createdAt": {
      "$date": "2025-11-19T04:26:06Z"
    },
    "updatedAt": {
      "$date": "2025-11-19T04:26:06Z"
    },
    "__v": 0
  },
  {
    "_id": {
      "$oid": "6a4352a2128caa7df6514207"
    },
    "productCode": "TNU041125",
    "productName": "Tóc tém siêu da TNU041125",
    "logType": "Sửa sản phẩm",
    "logAction": "Không có dữ liệu",
    "createdBy": "LÊ SỸ BÁCH",
    "createdAt": {
      "$date": "2025-11-04T09:30:27Z"
    },
    "updatedAt": {
      "$date": "2025-11-04T09:30:27Z"
    },
    "__v": 0
  },
  {
    "_id": {
      "$oid": "6a4352a2128caa7df6514208"
    },
    "productCode": "TNU231025",
    "productName": "TÓC TÉM SIÊU DA TNU231025",
    "logType": "Sửa sản phẩm",
    "logAction": "Sửa giá bán",
    "createdBy": "LÊ SỸ BÁCH",
    "createdAt": {
      "$date": "2025-11-04T09:27:49Z"
    },
    "updatedAt": {
      "$date": "2025-11-04T09:27:49Z"
    },
    "__v": 0
  },
  {
    "_id": {
      "$oid": "6a4352a2128caa7df6514209"
    },
    "productCode": "DDV2409251",
    "productName": "Đầu đội siêu da silk base DDV2409251",
    "logType": "Sửa sản phẩm",
    "logAction": "Sửa giá bán",
    "createdBy": "LÊ SỸ BÁCH",
    "createdAt": {
      "$date": "2025-11-04T09:27:15Z"
    },
    "updatedAt": {
      "$date": "2025-11-04T09:27:15Z"
    },
    "__v": 0
  },
  {
    "_id": {
      "$oid": "6a4352a2128caa7df651420a"
    },
    "productCode": "DDV2409251",
    "productName": "Đầu đội siêu da silk base DDV2409251",
    "logType": "Sửa sản phẩm",
    "logAction": "Không có dữ liệu",
    "createdBy": "LÊ SỸ BÁCH",
    "createdAt": {
      "$date": "2025-10-23T03:51:24Z"
    },
    "updatedAt": {
      "$date": "2025-10-23T03:51:24Z"
    },
    "__v": 0
  },
  {
    "_id": {
      "$oid": "6a4352a2128caa7df651420b"
    },
    "productCode": "TNU2409251",
    "productName": "TÓC TÉM TNU2409251",
    "logType": "Sửa sản phẩm",
    "logAction": "Sửa giá nhập",
    "createdBy": "LÊ SỸ BÁCH",
    "createdAt": {
      "$date": "2025-09-24T08:11:14Z"
    },
    "updatedAt": {
      "$date": "2025-09-24T08:11:14Z"
    },
    "__v": 0
  },
  {
    "_id": {
      "$oid": "6a4352a2128caa7df651420c"
    },
    "productCode": "DDV240925",
    "productName": "Đầu đội siêu da silk base DDV240925",
    "logType": "Sửa sản phẩm",
    "logAction": "Sửa giá nhập",
    "createdBy": "LÊ SỸ BÁCH",
    "createdAt": {
      "$date": "2025-09-24T08:10:52Z"
    },
    "updatedAt": {
      "$date": "2025-09-24T08:10:52Z"
    },
    "__v": 0
  },
  {
    "_id": {
      "$oid": "6a4352a2128caa7df651420d"
    },
    "productCode": "DDV6125",
    "productName": "Đầu đội silk base DDV6125",
    "logType": "Sửa sản phẩm",
    "logAction": "Không có dữ liệu",
    "createdBy": "LÊ SỸ BÁCH",
    "createdAt": {
      "$date": "2025-08-21T08:11:30Z"
    },
    "updatedAt": {
      "$date": "2025-08-21T08:11:30Z"
    },
    "__v": 0
  },
  {
    "_id": {
      "$oid": "6a4352a2128caa7df651420e"
    },
    "productCode": "MT1507",
    "productName": "Mái thưa MT1507",
    "logType": "Sửa sản phẩm",
    "logAction": "Không có dữ liệu",
    "createdBy": "LÊ SỸ BÁCH",
    "createdAt": {
      "$date": "2025-07-15T07:12:20Z"
    },
    "updatedAt": {
      "$date": "2025-07-15T07:12:20Z"
    },
    "__v": 0
  },
  {
    "_id": {
      "$oid": "6a4352a2128caa7df651420f"
    },
    "productCode": "UNKNOWN.49",
    "productName": "UNKNOWN",
    "logType": "Xóa sản phẩm",
    "logAction": "Không có dữ liệu",
    "createdBy": "LÊ SỸ BÁCH",
    "createdAt": {
      "$date": "2025-07-15T03:08:47Z"
    },
    "updatedAt": {
      "$date": "2025-07-15T03:08:47Z"
    },
    "__v": 0
  },
  {
    "_id": {
      "$oid": "6a4352a2128caa7df6514210"
    },
    "productCode": "VIC304",
    "productName": "VÍC305",
    "logType": "Sửa sản phẩm",
    "logAction": "Không có dữ liệu",
    "createdBy": "LÊ SỸ BÁCH",
    "createdAt": {
      "$date": "2025-07-15T03:01:43Z"
    },
    "updatedAt": {
      "$date": "2025-07-15T03:01:43Z"
    },
    "__v": 0
  },
  {
    "_id": {
      "$oid": "6a4352a2128caa7df6514211"
    },
    "productCode": "MHNU2607242",
    "productName": "Mái phủ 1 ngôi MHNU2607242",
    "logType": "Sửa sản phẩm",
    "logAction": "Không có dữ liệu",
    "createdBy": "LÊ SỸ BÁCH",
    "createdAt": {
      "$date": "2025-07-14T11:28:54Z"
    },
    "updatedAt": {
      "$date": "2025-07-14T11:28:54Z"
    },
    "__v": 0
  },
  {
    "_id": {
      "$oid": "6a4352a2128caa7df6514212"
    },
    "productCode": "MHNU2607241",
    "productName": "Mái phủ siêu da 1 ngôi MHNU2607241",
    "logType": "Sửa sản phẩm",
    "logAction": "Không có dữ liệu",
    "createdBy": "LÊ SỸ BÁCH",
    "createdAt": {
      "$date": "2025-07-14T11:16:42Z"
    },
    "updatedAt": {
      "$date": "2025-07-14T11:16:42Z"
    },
    "__v": 0
  },
  {
    "_id": {
      "$oid": "6a4352a2128caa7df6514213"
    },
    "productCode": "MHNA14071",
    "productName": "Mái phủ hói mono nam MHNA14071",
    "logType": "Sửa sản phẩm",
    "logAction": "Không có dữ liệu",
    "createdBy": "LÊ SỸ BÁCH",
    "createdAt": {
      "$date": "2025-07-14T11:07:49Z"
    },
    "updatedAt": {
      "$date": "2025-07-14T11:07:49Z"
    },
    "__v": 0
  },
  {
    "_id": {
      "$oid": "6a4352a2128caa7df6514214"
    },
    "productCode": "MHNA140725",
    "productName": "Mái phủ hói nam siêu da silk base",
    "logType": "Sửa sản phẩm",
    "logAction": "Không có dữ liệu",
    "createdBy": "LÊ SỸ BÁCH",
    "createdAt": {
      "$date": "2025-07-14T11:06:14Z"
    },
    "updatedAt": {
      "$date": "2025-07-14T11:06:14Z"
    },
    "__v": 0
  },
  {
    "_id": {
      "$oid": "6a4352a2128caa7df6514215"
    },
    "productCode": "HUYỀN-30125",
    "productName": "Mái phủ hói siêu da silk base MHNU30125",
    "logType": "Sửa sản phẩm",
    "logAction": "Không có dữ liệu",
    "createdBy": "LÊ SỸ BÁCH",
    "createdAt": {
      "$date": "2025-07-14T11:03:53Z"
    },
    "updatedAt": {
      "$date": "2025-07-14T11:03:53Z"
    },
    "__v": 0
  },
  {
    "_id": {
      "$oid": "6a4352a2128caa7df6514216"
    },
    "productCode": "MHNU0207254",
    "productName": "Mái hói siêu da đầu silk base MHNU0207254",
    "logType": "Sửa sản phẩm",
    "logAction": "Không có dữ liệu",
    "createdBy": "LÊ SỸ BÁCH",
    "createdAt": {
      "$date": "2025-07-02T08:18:32Z"
    },
    "updatedAt": {
      "$date": "2025-07-02T08:18:32Z"
    },
    "__v": 0
  },
  {
    "_id": {
      "$oid": "6a4352a2128caa7df6514217"
    },
    "productCode": "DDV2306251",
    "productName": "1Đầu đội siêu da silk base DDV2306251",
    "logType": "Sửa sản phẩm",
    "logAction": "Không có dữ liệu",
    "createdBy": "LÊ SỸ BÁCH",
    "createdAt": {
      "$date": "2025-06-23T10:54:16Z"
    },
    "updatedAt": {
      "$date": "2025-06-23T10:54:16Z"
    },
    "__v": 0
  },
  {
    "_id": {
      "$oid": "6a4352a2128caa7df6514218"
    },
    "productCode": "DDV230625",
    "productName": "Đầu đội siêu da silk base DDV230625",
    "logType": "Sửa sản phẩm",
    "logAction": "Không có dữ liệu",
    "createdBy": "LÊ SỸ BÁCH",
    "createdAt": {
      "$date": "2025-06-23T10:53:52Z"
    },
    "updatedAt": {
      "$date": "2025-06-23T10:53:52Z"
    },
    "__v": 0
  },
  {
    "_id": {
      "$oid": "6a4352a2128caa7df6514219"
    },
    "productCode": "HÂN-170425",
    "productName": "Đâu đội khách đặt DDV170425",
    "logType": "Sửa sản phẩm",
    "logAction": "Sửa giá bán",
    "createdBy": "LÊ SỸ BÁCH",
    "createdAt": {
      "$date": "2025-04-22T07:24:47Z"
    },
    "updatedAt": {
      "$date": "2025-04-22T07:24:47Z"
    },
    "__v": 0
  },
  {
    "_id": {
      "$oid": "6a4352a2128caa7df651421a"
    },
    "productCode": "MINH-160425",
    "productName": "Đâu đội khách đặt DDV160425",
    "logType": "Sửa sản phẩm",
    "logAction": "Không có dữ liệu",
    "createdBy": "LÊ SỸ BÁCH",
    "createdAt": {
      "$date": "2025-04-17T06:50:56Z"
    },
    "updatedAt": {
      "$date": "2025-04-17T06:50:56Z"
    },
    "__v": 0
  },
  {
    "_id": {
      "$oid": "6a4352a2128caa7df651421b"
    },
    "productCode": "MINH-170425",
    "productName": "Đâu đội siêu da SILK BASE DDV170425",
    "logType": "Sửa sản phẩm",
    "logAction": "Không có dữ liệu",
    "createdBy": "LÊ SỸ BÁCH",
    "createdAt": {
      "$date": "2025-04-17T06:50:42Z"
    },
    "updatedAt": {
      "$date": "2025-04-17T06:50:42Z"
    },
    "__v": 0
  },
  {
    "_id": {
      "$oid": "6a4352a2128caa7df651421c"
    },
    "productCode": "trang-0504253",
    "productName": "Mái phủ hói silk base MHNU0504253",
    "logType": "Sửa sản phẩm",
    "logAction": "Sửa giá bán",
    "createdBy": "LÊ SỸ BÁCH",
    "createdAt": {
      "$date": "2025-04-05T04:33:59Z"
    },
    "updatedAt": {
      "$date": "2025-04-05T04:33:59Z"
    },
    "__v": 0
  },
  {
    "_id": {
      "$oid": "6a4352a2128caa7df651421d"
    },
    "productCode": "UNKNOWN.63",
    "productName": "UNKNOWN",
    "logType": "Xóa sản phẩm",
    "logAction": "Không có dữ liệu",
    "createdBy": "LÊ SỸ BÁCH",
    "createdAt": {
      "$date": "2025-03-18T11:01:08Z"
    },
    "updatedAt": {
      "$date": "2025-03-18T11:01:08Z"
    },
    "__v": 0
  },
  {
    "_id": {
      "$oid": "6a4352a2128caa7df651421e"
    },
    "productCode": "MINH-183253",
    "productName": "Đầu đội siêu da silk base DDV183253",
    "logType": "Sửa sản phẩm",
    "logAction": "Sửa giá bán",
    "createdBy": "LÊ SỸ BÁCH",
    "createdAt": {
      "$date": "2025-03-18T11:00:59Z"
    },
    "updatedAt": {
      "$date": "2025-03-18T11:00:59Z"
    },
    "__v": 0
  },
  {
    "_id": {
      "$oid": "6a4352a2128caa7df651421f"
    },
    "productCode": "SEN-183252",
    "productName": "Đầu đội siêu da silk base DDV183252",
    "logType": "Sửa sản phẩm",
    "logAction": "Không có dữ liệu",
    "createdBy": "LÊ SỸ BÁCH",
    "createdAt": {
      "$date": "2025-03-18T10:58:37Z"
    },
    "updatedAt": {
      "$date": "2025-03-18T10:58:37Z"
    },
    "__v": 0
  },
  {
    "_id": {
      "$oid": "6a4352a2128caa7df6514220"
    },
    "productCode": "UNKNOWN.66",
    "productName": "UNKNOWN",
    "logType": "Sửa sản phẩm",
    "logAction": "Không có dữ liệu",
    "createdBy": "LÊ SỸ BÁCH",
    "createdAt": {
      "$date": "2025-03-18T10:57:52Z"
    },
    "updatedAt": {
      "$date": "2025-03-18T10:57:52Z"
    },
    "__v": 0
  },
  {
    "_id": {
      "$oid": "6a4352a2128caa7df6514221"
    },
    "productCode": "DDV183251",
    "productName": "Đầu đội siêu da silk base DDV183251",
    "logType": "Sửa sản phẩm",
    "logAction": "Sửa giá bán",
    "createdBy": "LÊ SỸ BÁCH",
    "createdAt": {
      "$date": "2025-03-18T10:57:11Z"
    },
    "updatedAt": {
      "$date": "2025-03-18T10:57:11Z"
    },
    "__v": 0
  },
  {
    "_id": {
      "$oid": "6a4352a2128caa7df6514222"
    },
    "productCode": "HÀ-18325",
    "productName": "Mái phủ hói silk base MNHU180325",
    "logType": "Sửa sản phẩm",
    "logAction": "Không có dữ liệu",
    "createdBy": "LÊ SỸ BÁCH",
    "createdAt": {
      "$date": "2025-03-18T10:56:29Z"
    },
    "updatedAt": {
      "$date": "2025-03-18T10:56:29Z"
    },
    "__v": 0
  },
  {
    "_id": {
      "$oid": "6a4352a2128caa7df6514223"
    },
    "productCode": "SEN-2112241",
    "productName": "Đầu đội siêu da silk base DDV2112241",
    "logType": "Sửa sản phẩm",
    "logAction": "Sửa giá bán",
    "createdBy": "LÊ SỸ BÁCH",
    "createdAt": {
      "$date": "2025-02-19T04:43:28Z"
    },
    "updatedAt": {
      "$date": "2025-02-19T04:43:28Z"
    },
    "__v": 0
  },
  {
    "_id": {
      "$oid": "6a4352a2128caa7df6514224"
    },
    "productCode": "SEN-2112241",
    "productName": "Đầu đội siêu da silk base DDV2112241",
    "logType": "Sửa sản phẩm",
    "logAction": "Sửa giá bán",
    "createdBy": "LÊ SỸ BÁCH",
    "createdAt": {
      "$date": "2025-02-18T08:52:45Z"
    },
    "updatedAt": {
      "$date": "2025-02-18T08:52:45Z"
    },
    "__v": 0
  },
  {
    "_id": {
      "$oid": "6a4352a2128caa7df6514225"
    },
    "productCode": "SEN-2112241",
    "productName": "Đầu đội siêu da silk base DDV2112241",
    "logType": "Sửa sản phẩm",
    "logAction": "Sửa giá bán",
    "createdBy": "LÊ SỸ BÁCH",
    "createdAt": {
      "$date": "2025-02-18T08:24:37Z"
    },
    "updatedAt": {
      "$date": "2025-02-18T08:24:37Z"
    },
    "__v": 0
  },
  {
    "_id": {
      "$oid": "6a4352a2128caa7df6514226"
    },
    "productCode": "UNKNOWN.72",
    "productName": "UNKNOWN",
    "logType": "Xóa sản phẩm",
    "logAction": "Không có dữ liệu",
    "createdBy": "LÊ SỸ BÁCH",
    "createdAt": {
      "$date": "2025-01-25T08:06:49Z"
    },
    "updatedAt": {
      "$date": "2025-01-25T08:06:49Z"
    },
    "__v": 0
  },
  {
    "_id": {
      "$oid": "6a4352a2128caa7df6514227"
    },
    "productCode": "MHNU071258",
    "productName": "Mái hói siêu da MHNU071258",
    "logType": "Sửa sản phẩm",
    "logAction": "Sửa giá bán",
    "createdBy": "LÊ SỸ BÁCH",
    "createdAt": {
      "$date": "2025-01-09T08:11:05Z"
    },
    "updatedAt": {
      "$date": "2025-01-09T08:11:05Z"
    },
    "__v": 0
  },
  {
    "_id": {
      "$oid": "6a4352a2128caa7df6514228"
    },
    "productCode": "MHNU07125",
    "productName": "Mái phủ hói 8*13 MHNU07125",
    "logType": "Sửa sản phẩm",
    "logAction": "Sửa giá bán",
    "createdBy": "LÊ SỸ BÁCH",
    "createdAt": {
      "$date": "2025-01-07T10:20:26Z"
    },
    "updatedAt": {
      "$date": "2025-01-07T10:20:26Z"
    },
    "__v": 0
  },
  {
    "_id": {
      "$oid": "6a4352a2128caa7df6514229"
    },
    "productCode": "UNKNOWN.75",
    "productName": "Mái phủ hói siêu da đầu MHNU301224",
    "logType": "Sửa sản phẩm",
    "logAction": "Sửa giá bán",
    "createdBy": "LÊ SỸ BÁCH",
    "createdAt": {
      "$date": "2024-12-30T07:18:10Z"
    },
    "updatedAt": {
      "$date": "2024-12-30T07:18:10Z"
    },
    "__v": 0
  },
  {
    "_id": {
      "$oid": "6a4352a2128caa7df651422a"
    },
    "productCode": "HUYỀN 21124",
    "productName": "Đầu đội siêu da silk base DDV21124",
    "logType": "Sửa sản phẩm",
    "logAction": "Sửa giá bán",
    "createdBy": "LÊ SỸ BÁCH",
    "createdAt": {
      "$date": "2024-12-03T08:33:14Z"
    },
    "updatedAt": {
      "$date": "2024-12-03T08:33:14Z"
    },
    "__v": 0
  },
  {
    "_id": {
      "$oid": "6a4352a2128caa7df651422b"
    },
    "productCode": "HUYEN -301124",
    "productName": "Mái hói siêu da silk base MHNU301124",
    "logType": "Sửa sản phẩm",
    "logAction": "Không có dữ liệu",
    "createdBy": "LÊ SỸ BÁCH",
    "createdAt": {
      "$date": "2024-12-03T08:32:01Z"
    },
    "updatedAt": {
      "$date": "2024-12-03T08:32:01Z"
    },
    "__v": 0
  },
  {
    "_id": {
      "$oid": "6a4352a2128caa7df651422c"
    },
    "productCode": "MHNU191124",
    "productName": "Mái phủ hói 1 ngôi MHNU191124",
    "logType": "Sửa sản phẩm",
    "logAction": "Không có dữ liệu",
    "createdBy": "LÊ SỸ BÁCH",
    "createdAt": {
      "$date": "2024-12-03T08:25:53Z"
    },
    "updatedAt": {
      "$date": "2024-12-03T08:25:53Z"
    },
    "__v": 0
  },
  {
    "_id": {
      "$oid": "6a4352a2128caa7df651422d"
    },
    "productCode": "MHNA82",
    "productName": "Mái Phủ Hói Nam siêu da Silk Base 82",
    "logType": "Sửa sản phẩm",
    "logAction": "Sửa giá nhập",
    "createdBy": "LÊ SỸ BÁCH",
    "createdAt": {
      "$date": "2024-12-03T06:50:15Z"
    },
    "updatedAt": {
      "$date": "2024-12-03T06:50:15Z"
    },
    "__v": 0
  },
  {
    "_id": {
      "$oid": "6a4352a2128caa7df651422e"
    },
    "productCode": "HÂN-271124",
    "productName": "Mái hói siêu da silk base MHNU271124",
    "logType": "Sửa sản phẩm",
    "logAction": "Sửa giá bán",
    "createdBy": "LÊ SỸ BÁCH",
    "createdAt": {
      "$date": "2024-11-27T04:01:48Z"
    },
    "updatedAt": {
      "$date": "2024-11-27T04:01:48Z"
    },
    "__v": 0
  },
  {
    "_id": {
      "$oid": "6a4352a2128caa7df651422f"
    },
    "productCode": "SEN 101124",
    "productName": "Đầu đội siêu da silk base DDV201124",
    "logType": "Sửa sản phẩm",
    "logAction": "Sửa giá bán",
    "createdBy": "LÊ SỸ BÁCH",
    "createdAt": {
      "$date": "2024-11-20T07:07:11Z"
    },
    "updatedAt": {
      "$date": "2024-11-20T07:07:11Z"
    },
    "__v": 0
  },
  {
    "_id": {
      "$oid": "6a4352a2128caa7df6514230"
    },
    "productCode": "MINH 2011241",
    "productName": "Đầu đội siêu da silk base DDV2011241",
    "logType": "Sửa sản phẩm",
    "logAction": "Sửa giá bán",
    "createdBy": "LÊ SỸ BÁCH",
    "createdAt": {
      "$date": "2024-11-20T07:06:49Z"
    },
    "updatedAt": {
      "$date": "2024-11-20T07:06:49Z"
    },
    "__v": 0
  },
  {
    "_id": {
      "$oid": "6a4352a2128caa7df6514231"
    },
    "productCode": "HÀ-DDN2308241",
    "productName": "Đầu đội siêu da Silkbase DDN2308241",
    "logType": "Sửa sản phẩm",
    "logAction": "Sửa giá bán",
    "createdBy": "LÊ SỸ BÁCH",
    "createdAt": {
      "$date": "2024-11-15T10:43:38Z"
    },
    "updatedAt": {
      "$date": "2024-11-15T10:43:38Z"
    },
    "__v": 0
  },
  {
    "_id": {
      "$oid": "6a4352a2128caa7df6514232"
    },
    "productCode": "MHNU131124",
    "productName": "mái hói có ngôi da đầu MHNU131124",
    "logType": "Sửa sản phẩm",
    "logAction": "Sửa giá bán",
    "createdBy": "LÊ SỸ BÁCH",
    "createdAt": {
      "$date": "2024-11-13T04:47:31Z"
    },
    "updatedAt": {
      "$date": "2024-11-13T04:47:31Z"
    },
    "__v": 0
  },
  {
    "_id": {
      "$oid": "6a4352a2128caa7df6514233"
    },
    "productCode": "UNKNOWN.85",
    "productName": "UNKNOWN",
    "logType": "Xóa sản phẩm",
    "logAction": "Không có dữ liệu",
    "createdBy": "LÊ SỸ BÁCH",
    "createdAt": {
      "$date": "2024-09-29T08:27:26Z"
    },
    "updatedAt": {
      "$date": "2024-09-29T08:27:26Z"
    },
    "__v": 0
  },
  {
    "_id": {
      "$oid": "6a4352a2128caa7df6514234"
    },
    "productCode": "HÀ-DDV280924",
    "productName": "ĐẦU ĐỘI NGÔI DDV280924",
    "logType": "Sửa sản phẩm",
    "logAction": "Không có dữ liệu",
    "createdBy": "LÊ SỸ BÁCH",
    "createdAt": {
      "$date": "2024-09-28T07:02:23Z"
    },
    "updatedAt": {
      "$date": "2024-09-28T07:02:23Z"
    },
    "__v": 0
  },
  {
    "_id": {
      "$oid": "6a4352a2128caa7df6514235"
    },
    "productCode": "HÀ-DDV280924",
    "productName": "ĐẦU ĐỘI NGÔI DDV280924",
    "logType": "Sửa sản phẩm",
    "logAction": "Không có dữ liệu",
    "createdBy": "LÊ SỸ BÁCH",
    "createdAt": {
      "$date": "2024-09-28T07:00:40Z"
    },
    "updatedAt": {
      "$date": "2024-09-28T07:00:40Z"
    },
    "__v": 0
  },
  {
    "_id": {
      "$oid": "6a4352a2128caa7df6514236"
    },
    "productCode": "SEN-MHNU2009241",
    "productName": "Mái siêu da silkbase MHNU2009241",
    "logType": "Sửa sản phẩm",
    "logAction": "Không có dữ liệu",
    "createdBy": "LÊ SỸ BÁCH",
    "createdAt": {
      "$date": "2024-09-20T04:46:51Z"
    },
    "updatedAt": {
      "$date": "2024-09-20T04:46:51Z"
    },
    "__v": 0
  },
  {
    "_id": {
      "$oid": "6a4352a2128caa7df6514237"
    },
    "productCode": "TNU 350",
    "productName": "Tém nữ 350",
    "logType": "Sửa sản phẩm",
    "logAction": "Sửa giá bán",
    "createdBy": "LÊ SỸ BÁCH",
    "createdAt": {
      "$date": "2024-08-15T10:18:11Z"
    },
    "updatedAt": {
      "$date": "2024-08-15T10:18:11Z"
    },
    "__v": 0
  },
  {
    "_id": {
      "$oid": "6a4352a2128caa7df6514238"
    },
    "productCode": "MPNA 007",
    "productName": "Mái Phủ Nam 07",
    "logType": "Sửa sản phẩm",
    "logAction": "Không có dữ liệu",
    "createdBy": "LÊ SỸ BÁCH",
    "createdAt": {
      "$date": "2024-08-15T10:16:06Z"
    },
    "updatedAt": {
      "$date": "2024-08-15T10:16:06Z"
    },
    "__v": 0
  },
  {
    "_id": {
      "$oid": "6a4352a2128caa7df6514239"
    },
    "productCode": "MPNA 007",
    "productName": "Mái Phủ Nam 07",
    "logType": "Sửa sản phẩm",
    "logAction": "Sửa giá bán",
    "createdBy": "LÊ SỸ BÁCH",
    "createdAt": {
      "$date": "2024-08-15T10:15:58Z"
    },
    "updatedAt": {
      "$date": "2024-08-15T10:15:58Z"
    },
    "__v": 0
  },
  {
    "_id": {
      "$oid": "6a4352a2128caa7df651423a"
    },
    "productCode": "MHN 401",
    "productName": "Mái Phủ Nam MHN401",
    "logType": "Sửa sản phẩm",
    "logAction": "Sửa giá bán",
    "createdBy": "LÊ SỸ BÁCH",
    "createdAt": {
      "$date": "2024-08-15T10:12:24Z"
    },
    "updatedAt": {
      "$date": "2024-08-15T10:12:24Z"
    },
    "__v": 0
  },
  {
    "_id": {
      "$oid": "6a4352a2128caa7df651423b"
    },
    "productCode": "K4062102",
    "productName": "Tóc kẹp 3 phím 35cm K4062102",
    "logType": "Sửa sản phẩm",
    "logAction": "Sửa giá bán",
    "createdBy": "LÊ SỸ BÁCH",
    "createdAt": {
      "$date": "2024-08-15T10:10:47Z"
    },
    "updatedAt": {
      "$date": "2024-08-15T10:10:47Z"
    },
    "__v": 0
  },
  {
    "_id": {
      "$oid": "6a4352a2128caa7df651423c"
    },
    "productCode": "MHNU191023",
    "productName": "Mái hói machine weft MHNU191023",
    "logType": "Sửa sản phẩm",
    "logAction": "Sửa giá bán",
    "createdBy": "LÊ SỸ BÁCH",
    "createdAt": {
      "$date": "2024-08-15T10:06:35Z"
    },
    "updatedAt": {
      "$date": "2024-08-15T10:06:35Z"
    },
    "__v": 0
  },
  {
    "_id": {
      "$oid": "6a4352a2128caa7df651423d"
    },
    "productCode": "TNU1904231",
    "productName": "TÉM NỮ TNU1904241",
    "logType": "Sửa sản phẩm",
    "logAction": "Sửa giá bán",
    "createdBy": "LÊ SỸ BÁCH",
    "createdAt": {
      "$date": "2024-08-15T10:00:25Z"
    },
    "updatedAt": {
      "$date": "2024-08-15T10:00:25Z"
    },
    "__v": 0
  },
  {
    "_id": {
      "$oid": "6a4352a2128caa7df651423e"
    },
    "productCode": "TNU190424",
    "productName": "Tóc tém TNU190424",
    "logType": "Sửa sản phẩm",
    "logAction": "Sửa giá bán",
    "createdBy": "LÊ SỸ BÁCH",
    "createdAt": {
      "$date": "2024-08-15T09:57:35Z"
    },
    "updatedAt": {
      "$date": "2024-08-15T09:57:35Z"
    },
    "__v": 0
  },
  {
    "_id": {
      "$oid": "6a4352a2128caa7df651423f"
    },
    "productCode": "HUYỀN- MHNU1008241",
    "productName": "Mái hói siêu da đầu silk base MHNU1008241",
    "logType": "Sửa sản phẩm",
    "logAction": "Không có dữ liệu",
    "createdBy": "LÊ SỸ BÁCH",
    "createdAt": {
      "$date": "2024-08-10T08:49:28Z"
    },
    "updatedAt": {
      "$date": "2024-08-10T08:49:28Z"
    },
    "__v": 0
  },
  {
    "_id": {
      "$oid": "6a4352a2128caa7df6514240"
    },
    "productCode": "HUYỀN-MHNU100824",
    "productName": "Mái hói siêu da đầu silk base MHNU100824",
    "logType": "Sửa sản phẩm",
    "logAction": "Không có dữ liệu",
    "createdBy": "LÊ SỸ BÁCH",
    "createdAt": {
      "$date": "2024-08-10T08:47:31Z"
    },
    "updatedAt": {
      "$date": "2024-08-10T08:47:31Z"
    },
    "__v": 0
  },
  {
    "_id": {
      "$oid": "6a4352a2128caa7df6514241"
    },
    "productCode": "HUYỀN-260724",
    "productName": "Đầu đội siêu da silk base DDV260724",
    "logType": "Sửa sản phẩm",
    "logAction": "Sửa giá bán",
    "createdBy": "LÊ SỸ BÁCH",
    "createdAt": {
      "$date": "2024-07-31T11:05:55Z"
    },
    "updatedAt": {
      "$date": "2024-07-31T11:05:55Z"
    },
    "__v": 0
  },
  {
    "_id": {
      "$oid": "6a4352a2128caa7df6514242"
    },
    "productCode": "UNKNOWN.100",
    "productName": "Đầu đội may tóc của khách",
    "logType": "Sửa sản phẩm",
    "logAction": "Không có dữ liệu",
    "createdBy": "LÊ SỸ BÁCH",
    "createdAt": {
      "$date": "2024-07-31T04:27:29Z"
    },
    "updatedAt": {
      "$date": "2024-07-31T04:27:29Z"
    },
    "__v": 0
  },
  {
    "_id": {
      "$oid": "6a4352a2128caa7df6514243"
    },
    "productCode": "HUYỀN-2607241",
    "productName": "Mái phủ hói siêu da silk base MHNU2607241",
    "logType": "Sửa sản phẩm",
    "logAction": "Sửa giá bán",
    "createdBy": "LÊ SỸ BÁCH",
    "createdAt": {
      "$date": "2024-07-26T08:23:45Z"
    },
    "updatedAt": {
      "$date": "2024-07-26T08:23:45Z"
    },
    "__v": 0
  },
  {
    "_id": {
      "$oid": "6a4352a2128caa7df6514244"
    },
    "productCode": "HÀ-240724",
    "productName": "Mái hói siêu da silk base MHNU240724",
    "logType": "Sửa sản phẩm",
    "logAction": "Sửa giá bán",
    "createdBy": "LÊ SỸ BÁCH",
    "createdAt": {
      "$date": "2024-07-24T09:09:12Z"
    },
    "updatedAt": {
      "$date": "2024-07-24T09:09:12Z"
    },
    "__v": 0
  },
  {
    "_id": {
      "$oid": "6a4352a2128caa7df6514245"
    },
    "productCode": "HUYỀN-2407244",
    "productName": "Mái phủ hói siêu da silk base MHNU2407244",
    "logType": "Sửa sản phẩm",
    "logAction": "Sửa giá bán",
    "createdBy": "LÊ SỸ BÁCH",
    "createdAt": {
      "$date": "2024-07-24T09:08:36Z"
    },
    "updatedAt": {
      "$date": "2024-07-24T09:08:36Z"
    },
    "__v": 0
  },
  {
    "_id": {
      "$oid": "6a4352a2128caa7df6514246"
    },
    "productCode": "HUYỀN DDV170624",
    "productName": "Đầu đội siêu da silk base DDV170624",
    "logType": "Sửa sản phẩm",
    "logAction": "Không có dữ liệu",
    "createdBy": "LÊ SỸ BÁCH",
    "createdAt": {
      "$date": "2024-07-05T11:04:12Z"
    },
    "updatedAt": {
      "$date": "2024-07-05T11:04:12Z"
    },
    "__v": 0
  },
  {
    "_id": {
      "$oid": "6a4352a2128caa7df6514247"
    },
    "productCode": "HÀ 220624-2",
    "productName": "đầu đội siêu da silkbase 220624",
    "logType": "Sửa sản phẩm",
    "logAction": "Không có dữ liệu",
    "createdBy": "LÊ SỸ BÁCH",
    "createdAt": {
      "$date": "2024-07-05T11:03:12Z"
    },
    "updatedAt": {
      "$date": "2024-07-05T11:03:12Z"
    },
    "__v": 0
  },
  {
    "_id": {
      "$oid": "6a4352a2128caa7df6514248"
    },
    "productCode": "HUYỀN  DDV280624",
    "productName": "Đầu đội siêu da silk base DDV280624",
    "logType": "Sửa sản phẩm",
    "logAction": "Không có dữ liệu",
    "createdBy": "LÊ SỸ BÁCH",
    "createdAt": {
      "$date": "2024-07-05T11:01:54Z"
    },
    "updatedAt": {
      "$date": "2024-07-05T11:01:54Z"
    },
    "__v": 0
  },
  {
    "_id": {
      "$oid": "6a4352a2128caa7df6514249"
    },
    "productCode": "HUYỀN  DDV280624",
    "productName": "Đầu đội siêu da silk base DDV280624",
    "logType": "Sửa sản phẩm",
    "logAction": "Không có dữ liệu",
    "createdBy": "LÊ SỸ BÁCH",
    "createdAt": {
      "$date": "2024-07-05T10:59:59Z"
    },
    "updatedAt": {
      "$date": "2024-07-05T10:59:59Z"
    },
    "__v": 0
  },
  {
    "_id": {
      "$oid": "6a4352a2128caa7df651424a"
    },
    "productCode": "MINH 020724-2",
    "productName": "đầu đội siêu da silkbase 020724",
    "logType": "Sửa sản phẩm",
    "logAction": "Không có dữ liệu",
    "createdBy": "LÊ SỸ BÁCH",
    "createdAt": {
      "$date": "2024-07-05T10:59:10Z"
    },
    "updatedAt": {
      "$date": "2024-07-05T10:59:10Z"
    },
    "__v": 0
  },
  {
    "_id": {
      "$oid": "6a4352a2128caa7df651424b"
    },
    "productCode": "HUYỀN DDV050724",
    "productName": "Đầu đội siêu da khách đặt DDV050724",
    "logType": "Sửa sản phẩm",
    "logAction": "Không có dữ liệu",
    "createdBy": "LÊ SỸ BÁCH",
    "createdAt": {
      "$date": "2024-07-05T10:58:14Z"
    },
    "updatedAt": {
      "$date": "2024-07-05T10:58:14Z"
    },
    "__v": 0
  },
  {
    "_id": {
      "$oid": "6a4352a2128caa7df651424c"
    },
    "productCode": "SEN DDV0507241",
    "productName": "Đầu đội siêu da SILK BASE DDV0507241",
    "logType": "Sửa sản phẩm",
    "logAction": "Không có dữ liệu",
    "createdBy": "LÊ SỸ BÁCH",
    "createdAt": {
      "$date": "2024-07-05T10:57:59Z"
    },
    "updatedAt": {
      "$date": "2024-07-05T10:57:59Z"
    },
    "__v": 0
  },
  {
    "_id": {
      "$oid": "6a4352a2128caa7df651424d"
    },
    "productCode": "HUYỀN  DDV280624",
    "productName": "Đầu đội siêu da silk base DDV280624",
    "logType": "Sửa sản phẩm",
    "logAction": "Sửa giá bán",
    "createdBy": "LÊ SỸ BÁCH",
    "createdAt": {
      "$date": "2024-06-28T11:30:06Z"
    },
    "updatedAt": {
      "$date": "2024-06-28T11:30:06Z"
    },
    "__v": 0
  },
  {
    "_id": {
      "$oid": "6a4352a2128caa7df651424e"
    },
    "productCode": "MHNU270124",
    "productName": "Mái hói siêu da đầu silk base MHNU270124",
    "logType": "Sửa sản phẩm",
    "logAction": "Sửa giá bán",
    "createdBy": "LÊ SỸ BÁCH",
    "createdAt": {
      "$date": "2024-06-28T11:08:35Z"
    },
    "updatedAt": {
      "$date": "2024-06-28T11:08:35Z"
    },
    "__v": 0
  },
  {
    "_id": {
      "$oid": "6a4352a2128caa7df651424f"
    },
    "productCode": "DDN110624",
    "productName": "Đầu đội pixel Đầu đội pixel DDN110624",
    "logType": "Sửa sản phẩm",
    "logAction": "Sửa giá bán",
    "createdBy": "LÊ SỸ BÁCH",
    "createdAt": {
      "$date": "2024-06-11T10:33:39Z"
    },
    "updatedAt": {
      "$date": "2024-06-11T10:33:39Z"
    },
    "__v": 0
  },
  {
    "_id": {
      "$oid": "6a4352a2128caa7df6514250"
    },
    "productCode": "UNKNOWN.114",
    "productName": "UNKNOWN",
    "logType": "Xóa sản phẩm",
    "logAction": "Không có dữ liệu",
    "createdBy": "LÊ SỸ BÁCH",
    "createdAt": {
      "$date": "2024-06-11T10:32:27Z"
    },
    "updatedAt": {
      "$date": "2024-06-11T10:32:27Z"
    },
    "__v": 0
  },
  {
    "_id": {
      "$oid": "6a4352a2128caa7df6514251"
    },
    "productCode": "UNKNOWN.115",
    "productName": "UNKNOWN",
    "logType": "Sửa sản phẩm",
    "logAction": "Sửa giá bán",
    "createdBy": "LÊ SỸ BÁCH",
    "createdAt": {
      "$date": "2024-06-11T10:31:55Z"
    },
    "updatedAt": {
      "$date": "2024-06-11T10:31:55Z"
    },
    "__v": 0
  },
  {
    "_id": {
      "$oid": "6a4352a2128caa7df6514252"
    },
    "productCode": "DDV1208231",
    "productName": "Đầu đội siêu da đầu silk base DDV1208231",
    "logType": "Sửa sản phẩm",
    "logAction": "Sửa giá bán",
    "createdBy": "LÊ SỸ BÁCH",
    "createdAt": {
      "$date": "2024-06-03T04:20:48Z"
    },
    "updatedAt": {
      "$date": "2024-06-03T04:20:48Z"
    },
    "__v": 0
  },
  {
    "_id": {
      "$oid": "6a4352a2128caa7df6514253"
    },
    "productCode": "UNKNOWN.117",
    "productName": "xịt dưỡng tóc XD41023",
    "logType": "Sửa sản phẩm",
    "logAction": "Không có dữ liệu",
    "createdBy": "LÊ SỸ BÁCH",
    "createdAt": {
      "$date": "2024-05-20T03:15:26Z"
    },
    "updatedAt": {
      "$date": "2024-05-20T03:15:26Z"
    },
    "__v": 0
  },
  {
    "_id": {
      "$oid": "6a4352a2128caa7df6514254"
    },
    "productCode": "MHNU170523",
    "productName": "Mái hói siêu da đầu silk base MHNU170523",
    "logType": "Sửa sản phẩm",
    "logAction": "Sửa giá bán",
    "createdBy": "LÊ SỸ BÁCH",
    "createdAt": {
      "$date": "2024-05-17T10:07:08Z"
    },
    "updatedAt": {
      "$date": "2024-05-17T10:07:08Z"
    },
    "__v": 0
  },
  {
    "_id": {
      "$oid": "6a4352a2128caa7df6514255"
    },
    "productCode": "DDN140524",
    "productName": "Đầu đội machine weft DDN140524",
    "logType": "Sửa sản phẩm",
    "logAction": "Sửa giá bán",
    "createdBy": "LÊ SỸ BÁCH",
    "createdAt": {
      "$date": "2024-05-14T03:12:20Z"
    },
    "updatedAt": {
      "$date": "2024-05-14T03:12:20Z"
    },
    "__v": 0
  },
  {
    "_id": {
      "$oid": "6a4352a2128caa7df6514256"
    },
    "productCode": "DDN140524",
    "productName": "Đầu đội machine weft DDN140524",
    "logType": "Sửa sản phẩm",
    "logAction": "Sửa giá bán",
    "createdBy": "LÊ SỸ BÁCH",
    "createdAt": {
      "$date": "2024-05-14T03:09:24Z"
    },
    "updatedAt": {
      "$date": "2024-05-14T03:09:24Z"
    },
    "__v": 0
  },
  {
    "_id": {
      "$oid": "6a4352a2128caa7df6514257"
    },
    "productCode": "DDN140524",
    "productName": "Đầu đội machine weft DDN140524",
    "logType": "Sửa sản phẩm",
    "logAction": "Sửa giá bán",
    "createdBy": "LÊ SỸ BÁCH",
    "createdAt": {
      "$date": "2024-05-14T03:08:38Z"
    },
    "updatedAt": {
      "$date": "2024-05-14T03:08:38Z"
    },
    "__v": 0
  }
]